<?xml version="1.0" encoding="utf-8"?>
<cms.alternativeform>
  <FormClassID>
    <CodeName>ecommerce.manufacturer</CodeName>
    <GUID>dcbcbc29-fa72-404c-bcaf-7eea0dac144e</GUID>
    <ObjectType>cms.systemtable</ObjectType>
  </FormClassID>
  <FormCustomizedColumns />
  <FormDefinition>
    <form>
      <field column="ManufacturerThumbnailGUID" order="5" />
      <field column="ManufacturerSiteID" visible="true" order="6">
        <settings>
          <Options>
<![CDATA[
{%SiteContext.CurrentSiteID|(identity)GlobalAdministrator|(hash)183952f13d5bf43eac0d8cdfb68eba8243e7acf80e3f14d9f2978eb34e873923%};{$com.onthissiteonly$}
;{$com.globally$}
]]>
          </Options>
          <SortItems>False</SortItems>
          <EditText>False</EditText>
          <controlname>dropdownlistcontrol</controlname>
        </settings>
        <properties>
          <visiblemacro>
            <![CDATA[{%Settings.CMSStoreAllowGlobalManufacturers && CurrentUser.IsAuthorizedPerResource("CMS.Ecommerce","EcommerceGlobalModify") && (CurrentUser.IsAuthorizedPerResource("CMS.Ecommerce","ModifyManufacturers") || CurrentUser.IsAuthorizedPerResource("CMS.Ecommerce","EcommerceModify"))|(identity)GlobalAdministrator|(hash)6c83dfbf504d4ca41fa59da8e2b658887cce0c87bdca07f555c72ac2eba2c18a%}]]>
          </visiblemacro>
          <defaultvalue ismacro="true">
<![CDATA[
{% if (!Settings.CMSStoreAllowGlobalManufacturers
    || !CurrentUser.IsAuthorizedPerResource("CMS.Ecommerce","EcommerceGlobalModify")
    || CurrentUser.IsAuthorizedPerResource("CMS.Ecommerce","ModifyManufacturers")
    || CurrentUser.IsAuthorizedPerResource("CMS.Ecommerce","EcommerceModify")) {SiteContext.CurrentSiteID} |(identity)GlobalAdministrator|(hash)f807a53e22be140fb2d310d02e887f3729b572aeb2aa90d98effb102f4ed68cf%}
]]>
          </defaultvalue>
          <fieldcaption>{$com.available$}</fieldcaption>
        </properties>
      </field>
      <field column="ManufacturerLastModified" order="7" />
      <field column="ManufacturerEnabled" visible="">
        <settings>
          <controlname />
        </settings>
        <properties>
          <fieldcaption />
        </properties>
      </field>
    </form>
  </FormDefinition>
  <FormDisplayName>Quick add</FormDisplayName>
  <FormGUID>2e2bdff0-75cf-46b3-9841-e025385ae446</FormGUID>
  <FormHideNewParentFields>False</FormHideNewParentFields>
  <FormIsCustom>False</FormIsCustom>
  <FormName>quickadd</FormName>
</cms.alternativeform>